jeelink/__init__.py
jeelink/device.py
jeelink/gateway.py
jeelink/helper.py
jeelink/pca.py
jeelink_python-0.1.dist-info/METADATA
jeelink_python-0.1.dist-info/WHEEL
jeelink_python-0.1.dist-info/top_level.txt
jeelink_python-0.1.dist-info/RECORD
