Metadata-Version: 2.1
Name: jeelink-python
Version: 0.1
Home-page: https://github.com/Andre0512/jeelink-python
Author: Andre Basche
License: MIT
Keywords: smart home automation
Platform: any
Requires-Python: >=3.8
Requires-Dist: pyserial
Requires-Dist: pyserial-asyncio
